{
  "id": "snapshot-1779517772941-5871-a98d9673",
  "timestamp": "2026-05-23T06:29:32.941Z",
  "symbol": "NVDA",
  "marketState": {
    "momentum": "UNKNOWN",
    "volatility": "UNKNOWN",
    "directionalBias": "UNKNOWN",
    "compression": "UNKNOWN"
  },
  "regime": {
    "type": "UNKNOWN",
    "confidence": 0.1,
    "reasons": [
      "Insufficient candle memory for regime classification."
    ]
  },
  "confidenceLevel": "LOW",
  "strategicEnvironment": "CAUTION",
  "consensusStrength": "WEAK",
  "anomalySeverity": "NONE",
  "runtimeStatus": "STABLE",
  "behavioralState": "UNKNOWN",
  "memoryImportance": "IGNORE",
  "summary": "NVDA strategic snapshot: CAUTION environment, WEAK consensus, STABLE runtime."
}