{
  "id": "snapshot-1779516384665-4492-f2dc8c2c",
  "timestamp": "2026-05-23T06:06:24.664Z",
  "symbol": "NVDA",
  "marketState": {
    "momentum": "UNKNOWN",
    "volatility": "UNKNOWN",
    "directionalBias": "UNKNOWN",
    "compression": "UNKNOWN"
  },
  "regime": {
    "type": "UNKNOWN",
    "confidence": 0.1,
    "reasons": [
      "Insufficient candle memory for regime classification."
    ]
  },
  "confidenceLevel": "LOW",
  "strategicEnvironment": "CAUTION",
  "consensusStrength": "WEAK",
  "anomalySeverity": "NONE",
  "runtimeStatus": "STABLE",
  "behavioralState": "UNKNOWN",
  "memoryImportance": "IGNORE",
  "summary": "NVDA strategic snapshot: CAUTION environment, WEAK consensus, STABLE runtime."
}